eurosat/__init__.py
eurosat_dataset-0.0.2.dist-info/LICENSE
eurosat_dataset-0.0.2.dist-info/METADATA
eurosat_dataset-0.0.2.dist-info/WHEEL
eurosat_dataset-0.0.2.dist-info/entry_points.txt
eurosat_dataset-0.0.2.dist-info/top_level.txt
eurosat_dataset-0.0.2.dist-info/RECORD
