Metadata-Version: 2.1
Name: eurosat-dataset
Version: 0.0.2
Summary: EUROSAT dataset loaders
Home-page: UNKNOWN
Author: DEEL
Author-email: collaborateurs.du.projet.deel@irt-saintexupery.com
License: UNKNOWN
Platform: UNKNOWN
Classifier: Programming Language :: Python
Classifier: Programming Language :: Python :: 3
Classifier: Programming Language :: Python :: 3.6
Classifier: Programming Language :: Python :: 3.7
License-File: LICENSE
Requires-Dist: deel-datasets
